iCallSV/FilterDellyCalls.py
iCallSV/Run_Delly.py
iCallSV/Run_iAnnotateSV.py
iCallSV/Run_samblaster.py
iCallSV/Run_targetSeqView.py
iCallSV/__init__.py
iCallSV/checkBlackList.py
iCallSV/checkHotSpotList.py
iCallSV/checkparameters.py
iCallSV/combineVCF.py
iCallSV/dellyVcf2Tab.py
iCallSV/dellyVcf2targetSeqView.py
iCallSV/filterAnnotatedSV.py
iCallSV/helper.py
iCallSV/iCallSV.py
iCallSV/launchThreads.py
iCallSV/launch_FilterDellyCalls.py
iCallSV/launch_Run_Delly.py
iCallSV/make_analysis_dir.py
iCallSV/makebamindex.py
iCallSV/mergeFinalFiles.py
iCallSV/sortbamByCoordinate.py
iCallSV/sortbamByReadName.py
iCallSV/R/install_requrements_targetSeqView.txt
iCallSV/R/Rscripts/calculateConfidenceScore.R
iCallSV/data/blacklist.txt
iCallSV/data/blacklistgenes.txt
iCallSV/data/genesToInclude.txt
iCallSV/data/hotspotgenes.txt
iCallSV/utilities/check_cDNA_contamination.py
iCallSV/utilities/iCallSV_dmp_wrapper.py
iCallSV-0.0.7.dist-info/DESCRIPTION.rst
iCallSV-0.0.7.dist-info/METADATA
iCallSV-0.0.7.dist-info/RECORD
iCallSV-0.0.7.dist-info/WHEEL
iCallSV-0.0.7.dist-info/metadata.json
iCallSV-0.0.7.dist-info/top_level.txt
