Metadata-Version: 2.0
Name: iCallSV
Version: 0.0.7
Summary: The module helps to call structural variants using NGS data set on human.
Home-page: https://github.com/rhshah/iCallSV
Author: Ronak H Shah
Author-email: rons.shah@gmail.com
License: Apache Software License
Download-URL: https://github.com/rhshah/iCallSV/tarball/0.0.7
Platform: any
Classifier: Programming Language :: Python
Classifier: Programming Language :: Python :: 2.7
Classifier: License :: OSI Approved :: Apache Software License
Classifier: Operating System :: OS Independent
Classifier: Intended Audience :: Science/Research
Classifier: Topic :: Scientific/Engineering :: Bio-Informatics
Classifier: Development Status :: 5 - Production/Stable
Requires-Python: >=2.6, !=3.0.*, !=3.1.*, !=3.2.*, <4
Requires-Dist: biopython (==1.65)
Requires-Dist: coloredlogs (==5.2)
Requires-Dist: pandas (==0.16.2)
Requires-Dist: pysam (==0.8.4)
Requires-Dist: pyvcf (==0.6.7)
